{
  "Main" : {
    "uid" : {
      "type" : "UID",
      "config" : {
        "label" : "uid"
      }
    },
    "title" : {
      "type" : "StructuredText",
      "config" : {
        "label" : "Title",
        "single" : "paragraph",
        "useAsTitle" : true
      }
    },
    "description" : {
      "type" : "StructuredText",
      "config" : {
        "label" : "Description",
        "single" : "paragraph"
      }
    },
    "section" : {
      "fieldset" : "Section",
      "type" : "Slices",
      "config" : {
        "choices" : {
          "series" : {
            "type" : "Link",
            "fieldset" : "Series",
            "config" : {
              "select" : "document",
              "label" : "Series",
              "customtypes" : [ "series" ]
            }
          }
        }
      }
    }
  }
}
